lfmaptools/__init__.py
lfmaptools/demtools.py
lfmaptools/epsg_defs.py
lfmaptools/geotools.py
lfmaptools/interptools.py
lfmaptools/lfclass.py
lfmaptools/mapping.py
lfmaptools/netcdf_utils.py
lfmaptools/utilities.py
lfmaptools-0.0.64.dist-info/LICENCE
lfmaptools-0.0.64.dist-info/METADATA
lfmaptools-0.0.64.dist-info/WHEEL
lfmaptools-0.0.64.dist-info/top_level.txt
lfmaptools-0.0.64.dist-info/RECORD
